elePyant/__init__.py
elePyant/core.py
elePyant/test/__init__.py
elePyant/test/test_core.py
elePyant-0.0.2.data/data/da_test.nc
elePyant-0.0.2.data/data/ds_test.nc
elePyant-0.0.2.dist-info/LICENSE
elePyant-0.0.2.dist-info/METADATA
elePyant-0.0.2.dist-info/WHEEL
elePyant-0.0.2.dist-info/top_level.txt
elePyant-0.0.2.dist-info/RECORD
