Metadata-Version: 2.1
Name: elePyant
Version: 0.0.2
Summary: Package that performs compression by rounding.
Home-page: https://github.com/fraserwg/elePyant/releases/tag/v0.0.2
Author: Fraser Goldsworth
Author-email: fraser.goldsworth@physics.ox.ac.uk
License: LICENSE
Download-URL: https://github.com/fraserwg/elePyant/archive/v0.0.2.tar.gz
Platform: UNKNOWN
Requires-Dist: xarray
Requires-Dist: numpy
Requires-Dist: h5netcdf
